geometor/__init__.py
geometor/model.py
geometor/pappus.py
geometor/render.py
geometor/spirals.py
geometor/utils.py
geometor-0.0.2.dist-info/METADATA
geometor-0.0.2.dist-info/WHEEL
geometor-0.0.2.dist-info/top_level.txt
geometor-0.0.2.dist-info/RECORD
